copasul/__init__.py
copasul/copasul.py
copasul/copasul_augment.py
copasul/copasul_clst.py
copasul/copasul_export.py
copasul/copasul_init.py
copasul/copasul_plot.py
copasul/copasul_preproc.py
copasul/copasul_resyn.py
copasul/copasul_sigproc.py
copasul/copasul_styl.py
copasul/copasul_utils.py
copasul/praat_utils.py
copasul-1.5.3.dist-info/LICENSE
copasul-1.5.3.dist-info/METADATA
copasul-1.5.3.dist-info/WHEEL
copasul-1.5.3.dist-info/top_level.txt
copasul-1.5.3.dist-info/RECORD
