Metadata-Version: 2.1
Name: copasul
Version: 1.5.3
Summary: Prosody stylization
Home-page: https://github.com/reichelu/copasul
Author: Uwe Reichel
Author-email: uwe.reichel@nytud.mta.hu
Project-URL: repository, https://github.com/reichelu/copasul
Project-URL: documentation, https://github.com/reichelu/copasul
Project-URL: article, https://arxiv.org/abs/1612.04765
Classifier: Programming Language :: Python :: 3
Classifier: License :: OSI Approved :: MIT License
Classifier: Operating System :: OS Independent
Classifier: Development Status :: 4 - Beta
Classifier: Topic :: Scientific/Engineering
Requires-Python: >=3.8
License-File: LICENSE
Requires-Dist: audeer
Requires-Dist: matplotlib
Requires-Dist: numpy
Requires-Dist: pandas
Requires-Dist: praat-parselmouth
Requires-Dist: scikit-learn
Requires-Dist: scipy
Requires-Dist: tqdm
